pycpplink/__init__.py
pycpplink/_core.cp312-win_amd64.pyd
pycpplink/advanced_low_level.cpp
pycpplink/wrapper.py
pycpplink-0.1.0.dist-info/METADATA
pycpplink-0.1.0.dist-info/WHEEL
pycpplink-0.1.0.dist-info/top_level.txt
pycpplink-0.1.0.dist-info/RECORD
