Metadata-Version: 2.4
Name: PyCppLink
Version: 0.1.0
Summary: Python wrapper for advanced C++ low-level operations
Home-page: https://github.com/mcjava20/Pycpplink
Author: Your Name
Author-email: Your Name <litten_iop@126.com>
License: MIT
Project-URL: Homepage, https://github.com/mcjava20/Pycpplink
Project-URL: Repository, https://github.com/mcjava20/Pycpplink
Project-URL: Bug Tracker, https://github.com/mcjava20/Pycpplink/issues
Keywords: c++,python,binding,wrapper,low-level,memory,performance
Classifier: Development Status :: 3 - Alpha
Classifier: Intended Audience :: Developers
Classifier: Programming Language :: Python :: 3
Classifier: Programming Language :: Python :: 3.7
Classifier: Programming Language :: Python :: 3.8
Classifier: Programming Language :: Python :: 3.9
Classifier: Programming Language :: Python :: 3.10
Classifier: Programming Language :: Python :: 3.11
Classifier: Programming Language :: Python :: 3.12
Classifier: Programming Language :: C++
Classifier: Operating System :: OS Independent
Classifier: Topic :: Software Development :: Libraries :: Python Modules
Requires-Python: >=3.7
Provides-Extra: dev
Requires-Dist: pytest>=7.0; extra == "dev"
Requires-Dist: pytest-cov>=4.0; extra == "dev"
Requires-Dist: black>=23.0; extra == "dev"
Requires-Dist: mypy>=1.0; extra == "dev"
Requires-Dist: flake8>=6.0; extra == "dev"
Requires-Dist: twine>=4.0; extra == "dev"
Requires-Dist: build>=0.10; extra == "dev"
Provides-Extra: docs
Requires-Dist: sphinx>=6.0; extra == "docs"
Requires-Dist: sphinx-rtd-theme>=1.0; extra == "docs"
Requires-Dist: myst-parser>=1.0; extra == "docs"
Dynamic: author
Dynamic: home-page
Dynamic: requires-python
